{
  "latestVersion": "1.0.2",
  "mandatory": true,
  "versions": [
    {
      "version": "1.0.2",
      "downloadUrl": "https://github.com/median0533/Malabar_Zewarcam/releases/download/v1.3.0/app-release.apk",
      "changelog": "✨ New features\n- Dark mode\n- Performance boost",
      "mandatory": true
    },
    {
      "version": "1.0.0",
      "downloadUrl": "https://github.com/median0533/Malabar_Zewarcam/releases/download/v1.2.0/app-release.apk",
      "changelog": "📸 Camera improvements"
    }
  ]
}
